pip_with_requires_python.py
pip_with_requires_python-1.0.1.dist-info/LICENSE
pip_with_requires_python-1.0.1.dist-info/WHEEL
pip_with_requires_python-1.0.1.dist-info/METADATA
pip_with_requires_python-1.0.1.dist-info/RECORD
